[
	{ "s": "И", "p": [14, 13, 32, 10, 9, 6, 2, 11, 5, 33, 24, 20, 19, 18, 15, 8, 7] },
	{ "s": "ИЗ", "p": [24, 19, 15] },
	{ "s": "ИЗМ", "p": [33] },
	{ "s": "ИЗМЕНЕН", "p": [33] },
	{ "s": "ИЗМЕНЕНИЕ", "p": [25] },
	{ "s": "ИЗМЕНЕНИЙ", "p": [33] },
	{ "s": "ИЗУЧЕНИИ", "p": [10] },
	{ "s": "ИЗУЧИТЕ", "p": [28] },
	{ "s": "ИЛИ", "p": [24, 17, 31, 25, 19, 11] },
	{ "s": "ИМ", "p": [1] },
	{ "s": "ИМЕНОВАНИЕ", "p": [21] },
	{ "s": "ИМЯ_ФАЙЛА", "p": [21] },
	{ "s": "ИНИЦИАЛИЗАЦИЯ", "p": [17] },
	{ "s": "ИНТЕРПРЕТИРОВАТЬ", "p": [7] },
	{ "s": "ИНТЕРФЕЙС", "p": [8] },
	{ "s": "ИНТЕРФЕЙСА", "p": [17] },
	{ "s": "ИНТЕРФЕЙСОМ", "p": [11, 7] },
	{ "s": "ИНФОРМАТИКИ", "p": [5] },
	{ "s": "ИНФОРМАЦИЕЙ", "p": [8] },
	{ "s": "ИНФОРМАЦИОННЫХ", "p": [1] },
	{ "s": "ИНФОРМАЦИЯ", "p": [6] },
	{ "s": "ИРИНА", "p": [1] },
	{ "s": "ИСКАЖЕНИЕ", "p": [26] },
	{ "s": "ИСПОЛНЯЕМОМУ", "p": [24, 15] },
	{ "s": "ИСПОЛНЯЕМЫЙ", "p": [13] },
	{ "s": "ИСПОЛЬЗОВАНИЯ", "p": [11, 8] },
	{ "s": "ИСПОЛЬЗОВАТЬСЯ", "p": [10] },
	{ "s": "ИСПОЛЬЗУЙТЕ", "p": [30, 25, 14] },
	{ "s": "ИССЛЕДОВАНИЕ", "p": [28] },
	{ "s": "ИССЛЕДОВАНИЯХ", "p": [10] },
	{ "s": "ИССЛЕДОВАТЕЛЕЙ", "p": [5] },
	{ "s": "ИССЛЕДОВАТЕЛЬСКИХ", "p": [11, 5] },
	{ "s": "ИСТОРИИ", "p": [6] },
	{ "s": "ИСТОРИЯ", "p": [15] },
	{ "s": "ИСТОЧНИКА", "p": [14] },
	{ "s": "ИХ", "p": [10] }
]